duckframe/__init__.py
duckframe-0.0.1.dist-info/METADATA
duckframe-0.0.1.dist-info/WHEEL
duckframe-0.0.1.dist-info/licenses/LICENSE
duckframe-0.0.1.dist-info/RECORD
