Metadata-Version: 2.3
Name: duckframe
Version: 0.0.1
Summary: coming soon?
Project-URL: Homepage, https://github.com/ibis-project/duckframe
Project-URL: Bug Tracker, https://github.com/ibis-project/duckframe
Author-email: Cody <cody@dkdc.dev>
License-File: LICENSE
Classifier: License :: OSI Approved :: MIT License
Classifier: Operating System :: OS Independent
Classifier: Programming Language :: Python :: 3
Requires-Python: >=3.11
Requires-Dist: ibis-framework[duckdb]
